{
    "methods": {
        "eth_getBlockReceipts": "erigon",
        "trace_block": "good",
        "trace_call": "erigon",
        "trace_get": "erigon",
        "trace_transaction": "erigon",
        "trace_filter": "good",
        "trace_rawTransaction": "erigon",
        "trace_replayTransaction": "erigon",
        "debug_traceBlockByHash": "good",
        "debug_traceBlockByNumber": "good",
        "debug_traceCall": "good",
        "debug_traceTransaction": "good",
        "eth_getLogs": "good",
        "newPendingTransactionFilter": "good",
        "txpool_content": "good"
    },
    "default": "",
    "default_archive": ""
}
